{
    "Sols": {
        "x(0, 2, 1)": 1.0,
        "x(0, P, 1)": 1.0,
        "x(1, P, 1)": 1.0,
        "x(2, 3, 1)": 1.0,
        "x(3, F2, 1)": 1.0,
        "x(F2, 1, 1)": 1.0
    },
    "demandi": {
        "0": 0,
        "1": 100,
        "2": 100,
        "3": 100,
        "F2": 0
    },
    "lijm": {
        "(0, 2, 1)": 300.0,
        "(0, 'P', 1)": 0.0,
        "(1, 'P', 1)": 0.0,
        "(2, 3, 1)": 200.0,
        "(3, 'F2', 1)": 100.0,
        "('F2', 1, 1)": 100.0
    },
    "energy_costs": {
        "(0, 2)": 30000,
        "(0, 'P')": 30000,
        "(1, 'P')": 30000,
        "(2, 3)": 30000,
        "(3, 'F2')": 30000,
        "('F2', 1)": 30000
    },
    "yim": {
        "(0, 1)": 90000.0,
        "(1, 1)": 30000.0,
        "(2, 1)": 60000.0,
        "(3, 1)": 30000.0,
        "('F2', 1)": 60000.0
    },
    "vim": {
        "(0, 1)": 90000.0,
        "('F2', 1)": 12000.0
    }
}